cv_validator/__init__.py
cv_validator/checks/__init__.py
cv_validator/checks/data/__init__.py
cv_validator/checks/data/brightness_check.py
cv_validator/checks/data/color_shift.py
cv_validator/checks/data/find_duplicates.py
cv_validator/checks/data/image_exist.py
cv_validator/checks/data/image_size.py
cv_validator/checks/data/label_distribution.py
cv_validator/checks/data/train_test_shift.py
cv_validator/checks/metric/__init__.py
cv_validator/checks/metric/metric_by_group.py
cv_validator/checks/metric/metric_check.py
cv_validator/checks/metric/metric_diff.py
cv_validator/core/__init__.py
cv_validator/core/check.py
cv_validator/core/condition.py
cv_validator/core/context.py
cv_validator/core/data.py
cv_validator/core/result.py
cv_validator/core/status.py
cv_validator/core/suite.py
cv_validator/utils/__init__.py
cv_validator/utils/check.py
cv_validator/utils/common.py
cv_validator/utils/data.py
cv_validator/utils/display.py
cv_validator/utils/embedding.py
cv_validator/utils/hashing.py
cv_validator/utils/image.py
cv_validator/utils/metric.py
cv_validator/utils/psi.py
cv_validator-0.1.4.dist-info/LICENSE.txt
cv_validator-0.1.4.dist-info/WHEEL
cv_validator-0.1.4.dist-info/METADATA
cv_validator-0.1.4.dist-info/RECORD
