Metadata-Version: 2.1
Name: cv-validator
Version: 0.1.4
Summary: Tool for validating your computer vision data and model results.
Home-page: https://github.com/ningeen/cv-validator
License: MIT
Author: Ruslan Sakaev
Author-email: sakaevruslan@gmail.com
Requires-Python: >=3.6.2,<3.11
Classifier: License :: OSI Approved :: MIT License
Classifier: Programming Language :: Python :: 3
Classifier: Programming Language :: Python :: 3.10
Classifier: Programming Language :: Python :: 3.7
Classifier: Programming Language :: Python :: 3.8
Classifier: Programming Language :: Python :: 3.9
Requires-Dist: ipython (>=7.16.3)
Requires-Dist: ipywidgets (>=7.6.5,<8.0.0)
Requires-Dist: joblib (>=1.1.0,<2.0.0)
Requires-Dist: numpy (>=1.19.5)
Requires-Dist: onnx (>=1.11.0,<2.0.0)
Requires-Dist: onnxruntime (>=1.9.0)
Requires-Dist: opencv-python (>=4.5.2,<5.0.0)
Requires-Dist: pandas (>=1.1.5)
Requires-Dist: plotly (>=5.6.0,<6.0.0)
Requires-Dist: scipy (>=1.5.4)
Requires-Dist: tqdm (>=4.62.3,<5.0.0)
